kstoolbox/__init__.py
kstoolbox-0.0.2.dist-info/LICENSE
kstoolbox-0.0.2.dist-info/METADATA
kstoolbox-0.0.2.dist-info/WHEEL
kstoolbox-0.0.2.dist-info/top_level.txt
kstoolbox-0.0.2.dist-info/RECORD
