Metadata-Version: 2.1
Name: kstoolbox
Version: 0.0.2
Summary: Small toolbox for AI Hackathon
Home-page: https://github.com/Rian-T/kstoolbox
Author: Rian Touchent
Author-email: riantouchent@gmail.com
License: UNKNOWN
Platform: UNKNOWN
Classifier: Programming Language :: Python :: 3
Classifier: License :: OSI Approved :: MIT License
Classifier: Operating System :: OS Independent
Requires-Python: >=3.6
